{
  "last_updated": "2026-05-02 12:05",
  "teams": [
    {
      "slug": "alabama",
      "espn_id": 148,
      "name": "Alabama",
      "abbr": "ALA",
      "color": "9E1B32",
      "logo": "",
      "record": "31-16",
      "sec_record": "12-11",
      "streak": "W2",
      "run_diff": 84,
      "next_game": {
        "game_date": "May 2, 2026",
        "day_of_week": "Sat",
        "time_ct": "1:00 PM",
        "location_type": "Home",
        "city": "Tuscaloosa, Alabama",
        "opponent": "Vanderbilt",
        "opponent_rank": null,
        "result": "Upcoming",
        "team_score": null,
        "opp_score": null,
        "innings": null,
        "is_conference": 1,
        "opp_wins": null,
        "opp_losses": null,
        "temp_hi": 70,
        "precip_in": 0.07,
        "wind_mph": 11,
        "weather_icon": "\ud83c\udf24",
        "weather_type": "actual"
      }
    }
  ]
}